{"expireTime":9007200877187166000,"key":"create-remote-file-node-https://dev-mercury-towers.pantheonsite.io/wp-content/uploads/Elementor-Pro-2.4.6-WordPress-Page-Builder.zip","val":{"connection":"close","content-length":"4083348","content-type":"application/zip","etag":"\"60b4904c-3e4e94\"","last-modified":"Mon, 31 May 2021 07:29:16 GMT","server":"nginx","strict-transport-security":"max-age=300","x-pantheon-styx-hostname":"styx-fe4-a-57ddb7f7f4-9hpzl","x-styx-req-id":"ec67c64f-c1e1-11eb-a1c3-be59b9a873a3","date":"Mon, 31 May 2021 07:29:27 GMT","x-served-by":"cache-mdw17320-MDW, cache-bom4741-BOM","x-cache":"HIT, MISS","x-cache-hits":"1, 0","x-timer":"S1622446166.949143,VS0,VE1102","x-robots-tag":"noindex","age":"1","accept-ranges":"bytes","via":"1.1 varnish, 1.1 varnish"}}